azbankintro/__init__.py
azbankintro/default_settings.py
azbankintro/enums.py
azbankintro/iban.py
azbankintro/exceptions/__init__.py
azbankintro/exceptions/cards.py
azbankintro/exceptions/iban.py
azbankintro/utils/__init__.py
azbankintro/utils/django_enum.py
azbankintro/validations/__init__.py
azbankintro/validations/cards.py
azbankintro/validations/iban.py
az_iranian_bank_intro-1.2.3.dist-info/LICENSE
az_iranian_bank_intro-1.2.3.dist-info/METADATA
az_iranian_bank_intro-1.2.3.dist-info/WHEEL
az_iranian_bank_intro-1.2.3.dist-info/top_level.txt
az_iranian_bank_intro-1.2.3.dist-info/RECORD
